baseballfaker/__init__.py
baseballfaker/baseball.py
BaseballFaker-0.0.3.dist-info/LICENSE
BaseballFaker-0.0.3.dist-info/METADATA
BaseballFaker-0.0.3.dist-info/WHEEL
BaseballFaker-0.0.3.dist-info/top_level.txt
BaseballFaker-0.0.3.dist-info/RECORD
