Metadata-Version: 2.1
Name: BaseballFaker
Version: 0.0.3
Summary: A small example package
Author-email: Josh Kolodny <kolo.josh@gmail.com>
Project-URL: Homepage, https://github.com/JKolodny/BaseballFaker
Project-URL: Bug Tracker, https://github.com/JKolodny/BaseballFaker/issues
Classifier: Programming Language :: Python :: 3
Classifier: License :: OSI Approved :: MIT License
Classifier: Operating System :: OS Independent
Requires-Python: >=3.7
License-File: LICENSE
Requires-Dist: faker
Requires-Dist: numpy
Requires-Dist: requests
